k8scjinja
